{
  "$schema": "design-tokens",
  "color": {
    "paper": { "value": "#faf7f1", "description": "primary background — warm off-white" },
    "paper2": { "value": "#f2ede2", "description": "recessed surface — sidebar, hover" },
    "paper3": { "value": "#e8e1d2", "description": "deepest paper — meter track" },
    "card": { "value": "#ffffff", "description": "elevated surface" },
    "ink": { "value": "#1a1612", "description": "primary text + active fill" },
    "ink2": { "value": "#3d362e", "description": "body copy (web)" },
    "inkSoft": { "value": "#5a5148", "description": "secondary text" },
    "inkMute": { "value": "#8a8074", "description": "tertiary / metadata" },
    "rule": { "value": "#d8d0bf", "description": "default border (web)" },
    "ruleMobile": { "value": "#e0d8c8", "description": "default border (mobile)" },
    "ruleStrong": { "value": "#c9bfac", "description": "high-contrast border" },
    "accent": { "value": "#c96442", "description": "primary accent (terracotta)" },
    "accent2": { "value": "#b15535", "description": "accent hover" },
    "accentSoft": { "value": "#f7e2d3", "description": "accent tint" },
    "hilite": { "value": "#f4d35e", "description": "highlight (amber)" },
    "hiliteSoft": { "value": "#fbeeb6", "description": "highlight wash" },
    "ok": { "value": "#5b8a5a", "description": "success (sage)" },
    "okSoft": { "value": "#d8e6d3", "description": "success tint" }
  },
  "font": {
    "display": { "value": "'Fraunces', 'Iowan Old Style', Georgia, serif", "description": "headlines, numbers, brand. Use weight 500. Variable opsz: 144." },
    "ui": { "value": "'Inter', system-ui, -apple-system, sans-serif", "description": "all UI text" },
    "mono": { "value": "'JetBrains Mono', ui-monospace, Menlo, monospace", "description": "codes (CEFR, slot indicators, numeric data with tabular-nums)" },
    "hand": { "value": "'Caveat', cursive", "description": "personality accent — coach voice, p.s. notes. Use weight 600. Sparingly."  }
  },
  "fontSize": {
    "displayXl": "56px",
    "displayL": "40px",
    "displayM": "28px",
    "displayS": "22px",
    "displayMobile": "26px",
    "bodyL": "17px",
    "body": "14px",
    "small": "12px",
    "micro": "11px"
  },
  "lineHeight": {
    "displayTight": 1.05,
    "display": 1.1,
    "displayMedium": 1.2,
    "body": 1.55,
    "ui": 1.4
  },
  "radius": {
    "sm": "6px",
    "md": "10px",
    "lg": "16px",
    "mobile3": "14px",
    "mobile4": "20px",
    "xl": "24px",
    "pill": "999px"
  },
  "spacing": {
    "1": "4px", "2": "8px", "3": "12px", "4": "16px",
    "5": "20px", "6": "24px", "7": "32px", "8": "40px"
  },
  "shadow": {
    "1": "0 1px 2px rgba(26,22,18,0.05), 0 1px 3px rgba(26,22,18,0.06)",
    "2": "0 2px 4px rgba(26,22,18,0.06), 0 8px 24px rgba(26,22,18,0.08)",
    "3": "0 4px 12px rgba(26,22,18,0.10), 0 24px 60px rgba(26,22,18,0.14)",
    "fab": "0 6px 18px rgba(26,22,18,0.30)",
    "sheet": "0 -10px 40px rgba(0,0,0,0.18)"
  },
  "tapTarget": {
    "primary": "48px",
    "medium": "40px",
    "small": "32px"
  },
  "viewport": {
    "webMaxContent": "1100px",
    "webNavWidth": "220px",
    "mobileWidth": "412px",
    "mobileHeight": "892px"
  }
}
